Metadata-Version: 2.1
Name: hf-image-uploader
Version: 0.0.1
Summary: State-of-the-art diffusion in PyTorch and JAX.
Home-page: https://github.com/patrickvonplaten/image_uploader
Author: The HuggingFace team
Author-email: patrick@huggingface.co
License: Apache
Keywords: deep learning diffusion jax pytorch stable diffusion audioldm
Platform: UNKNOWN
Classifier: Development Status :: 5 - Production/Stable
Classifier: Intended Audience :: Developers
Classifier: Intended Audience :: Education
Classifier: Intended Audience :: Science/Research
Classifier: License :: OSI Approved :: Apache Software License
Classifier: Operating System :: OS Independent
Classifier: Programming Language :: Python :: 3
Classifier: Programming Language :: Python :: 3.7
Classifier: Programming Language :: Python :: 3.8
Classifier: Programming Language :: Python :: 3.9
Classifier: Topic :: Scientific/Engineering :: Artificial Intelligence
Requires-Python: >=3.7.0
